generator/__init__.py
generator/analytics.py
generator/cli.py
generator/cloud_deployer.py
generator/config_manager.py
generator/project_browser.py
generator/prompts.py
generator/renderer.py
generator/template_customizer.py
generator/utils.py
generator/validator.py
generator/validators.py
mlops_project_generator-1.0.7.dist-info/licenses/LICENSE
mlops_project_generator-1.0.7.dist-info/METADATA
mlops_project_generator-1.0.7.dist-info/WHEEL
mlops_project_generator-1.0.7.dist-info/entry_points.txt
mlops_project_generator-1.0.7.dist-info/top_level.txt
mlops_project_generator-1.0.7.dist-info/RECORD
