Metadata-Version: 2.4
Name: mlops-project-generator
Version: 1.0.7
Summary: A CLI tool that generates production-ready MLOps project templates for Scikit-learn, PyTorch, and TensorFlow
Author-email: HARSHHAA <contact@example.com>
Maintainer-email: HARSHHAA <contact@example.com>
License: MIT
Project-URL: Homepage, https://github.com/NotHarshhaa/MLOps-Project-Generator
Project-URL: Documentation, https://github.com/NotHarshhaa/MLOps-Project-Generator#readme
Project-URL: Repository, https://github.com/NotHarshhaa/MLOps-Project-Generator.git
Project-URL: Bug Tracker, https://github.com/NotHarshhaa/MLOps-Project-Generator/issues
Keywords: mlops,machine-learning,project-generator,cli,template,scikit-learn,pytorch,tensorflow
Classifier: Development Status :: 4 - Beta
Classifier: Intended Audience :: Developers
Classifier: Intended Audience :: Science/Research
Classifier: Operating System :: OS Independent
Classifier: Programming Language :: Python :: 3
Classifier: Programming Language :: Python :: 3.8
Classifier: Programming Language :: Python :: 3.9
Classifier: Programming Language :: Python :: 3.10
Classifier: Programming Language :: Python :: 3.11
Classifier: Programming Language :: Python :: 3.12
Classifier: Topic :: Scientific/Engineering :: Artificial Intelligence
Classifier: Topic :: Software Development :: Code Generators
Classifier: Topic :: Software Development :: Libraries :: Python Modules
Classifier: Topic :: System :: Systems Administration
Requires-Python: >=3.8
License-File: LICENSE
Requires-Dist: typer[all]>=0.9.0
Requires-Dist: rich>=13.0.0
Requires-Dist: jinja2>=3.0.0
Requires-Dist: pydantic>=2.0.0
Requires-Dist: click>=8.0.0
Provides-Extra: dev
Requires-Dist: pytest>=7.0.0; extra == "dev"
Requires-Dist: pytest-cov>=4.0.0; extra == "dev"
Requires-Dist: black>=23.0.0; extra == "dev"
Requires-Dist: isort>=5.12.0; extra == "dev"
Requires-Dist: flake8>=6.0.0; extra == "dev"
Requires-Dist: mypy>=1.0.0; extra == "dev"
Requires-Dist: pre-commit>=3.0.0; extra == "dev"
Dynamic: license-file
